{
  "concertId": "s06-2021-10-11-dont-look-down",
  "title": "Don't Look Down",
  "subtitle": "(featuring Conor Hanick)",
  "date": "2021-10-11",
  "venue": "first-congregational-church",
  "description": "Yaz Lancaster's Sequoia opens our season with ethereal, reflective sounds that remind us of the importance and intimacy of being together in the concert hall. Conor Hanick returns with the second ever performance of Chris Cerrone's poignant work, Don't Look Down, for percussion quartet and piano, named one of The New York Times' Best Pieces of 2020. Two years in the making, Max Grafe's Shadow Theater, composed specifically for George, Samantha and Conor, will finally receive its premiere.",
  "sponsors": [
    "The Gardener Foundation"
  ],
  "program": [
    {
      "workId": "yaz-lancaster-sequoia-for-percussion-2019",
      "instrumentation": [
        {
          "instrument": "percussion",
          "count": 2,
          "musicians": [
            "George Nickson",
            "Charlie Rosmarin"
          ]
        }
      ]
    },
    {
      "workId": "max-grafe-shadow-theater-for-violin-piano-and-percussion-2020",
      "instrumentation": [
        {
          "instrument": "violin",
          "musicians": [
            "Samantha Bennett"
          ]
        },
        {
          "instrument": "piano",
          "musicians": [
            "Conor Hanick"
          ]
        },
        {
          "instrument": "percussion",
          "musicians": [
            "George Nickson"
          ]
        }
      ]
    },
    {
      "workId": "christopher-cerrone-don-t-look-down-for-prepared-piano-and-percussion-quartet-2020",
      "instrumentation": [
        {
          "instrument": "piano",
          "musicians": [
            "Conor Hanick"
          ]
        },
        {
          "instrument": "percussion",
          "count": 4,
          "musicians": [
            "George Nickson",
            "Charlie Rosmarin",
            "Scott Crawford",
            "Isaac Fernandez Hernandez"
          ]
        }
      ]
    }
  ]
}