{
  "concertId": "s09-2025-01-13-visions-and-miracles",
  "title": "Visions and Miracles",
  "date": "2025-01-13",
  "venue": "first-congregational-church",
  "program": [
    {
      "workId": "anna-clyne-rest-these-hands",
      "instrumentation": [
        {
          "instrument": "violin",
          "musicians": []
        }
      ]
    },
    {
      "workId": "chris-theofanidis-visions-and-miracles",
      "instrumentation": [
        {
          "instrument": "violins",
          "count": 2,
          "musicians": []
        },
        {
          "instrument": "viola",
          "musicians": []
        },
        {
          "instrument": "cello",
          "musicians": []
        }
      ]
    },
    {
      "workId": "dai-wei-how-the-stars-vanish",
      "instrumentation": [
        {
          "instrument": "flute",
          "musicians": []
        },
        {
          "instrument": "clarinet",
          "musicians": []
        },
        {
          "instrument": "violin",
          "musicians": []
        },
        {
          "instrument": "cello",
          "musicians": []
        }
      ]
    },
    {
      "workId": "han-lash-how-to-remember-seeds",
      "instrumentation": [
        {
          "instrument": "violins",
          "count": 2,
          "musicians": []
        },
        {
          "instrument": "viola",
          "musicians": []
        },
        {
          "instrument": "cello",
          "musicians": []
        }
      ]
    },
    {
      "workId": "gabriela-lena-frank-milagros",
      "instrumentation": [
        {
          "instrument": "violins",
          "count": 2,
          "musicians": []
        },
        {
          "instrument": "viola",
          "musicians": []
        },
        {
          "instrument": "cello",
          "musicians": []
        }
      ]
    }
  ]
}